sd_spider_utils/__init__.py
sd_spider_utils/common_spider.py
sd_spider_utils/common_utils.py
sd_spider_utils/data_utils.py
sd_spider_utils/datetime_utils.py
sd_spider_utils/parse_utils.py
sd_spider_utils/spider_demos.py
sd_spider_utils/text_utils.py
sd_spider_utils/url_utils.py
sd_spider_utils-1.0.2.dist-info/licenses/LICENSE
sd_spider_utils-1.0.2.dist-info/METADATA
sd_spider_utils-1.0.2.dist-info/WHEEL
sd_spider_utils-1.0.2.dist-info/top_level.txt
sd_spider_utils-1.0.2.dist-info/RECORD
